match_predicting_pub/__init__.py
match_predicting_pub/api/__init__.py
match_predicting_pub/api/api_client.py
match_predicting_pub/api/api_response.py
match_predicting_pub/api/configuration.py
match_predicting_pub/api/exceptions.py
match_predicting_pub/api/py.typed
match_predicting_pub/api/rest.py
match_predicting_pub/api/api/__init__.py
match_predicting_pub/api/api/dummy_api.py
match_predicting_pub/api/api/import_api.py
match_predicting_pub/api/api/testing_api.py
match_predicting_pub/api/api/training_api.py
match_predicting_pub/api/models/__init__.py
match_predicting_pub/api/models/dummy_dto.py
match_predicting_pub/api/models/fcm_topic.py
match_predicting_pub/api/models/import_dto.py
match_predicting_pub/api/models/import_progress_dto.py
match_predicting_pub/api/models/import_type.py
match_predicting_pub/api/models/progress_dto.py
match_predicting_pub/api/models/testing_dto.py
match_predicting_pub/api/models/training_dto.py
match_predicting_pub/api/models/training_network_dto.py
match_predicting_pub/api/models/training_progress_dto.py
match_predicting_pub/api/models/training_request_dto.py
match_predicting_pub/api/models/training_result_dto.py
match_predicting_pub/api/models/user_role_enum.py
match_predicting_public_api_python-4.8.dist-info/METADATA
match_predicting_public_api_python-4.8.dist-info/WHEEL
match_predicting_public_api_python-4.8.dist-info/top_level.txt
match_predicting_public_api_python-4.8.dist-info/RECORD
