Metadata-Version: 2.4
Name: match-predicting-public-api-python
Version: 4.8
Summary: Match Predicting Application Public API
Home-page: 
Author: István Mag
Author-email: magistvan@yahoo.com
Keywords: Match Predicting Application Public API
Requires-Dist: urllib3<3.0.0,>=1.25.3
Requires-Dist: python-dateutil
Requires-Dist: pydantic<2,>=1.10.5
Requires-Dist: aenum
Dynamic: author
Dynamic: author-email
Dynamic: description
Dynamic: description-content-type
Dynamic: keywords
Dynamic: requires-dist
Dynamic: summary
